{
  "project_info": {
    "project_number": "969750039725",
    "project_id": "onlineshopcoffee-53ab2",
    "storage_bucket": "onlineshopcoffee-53ab2.appspot.com"
  },
  "client": [
    {
      "client_info": {
        "mobilesdk_app_id": "1:969750039725:android:7168b5d58a8ca2e8b54a24",
        "android_client_info": {
          "package_name": "com.ar4uk.onlineshopcoffee"
        }
      },
      "oauth_client": [],
      "api_key": [
        {
          "current_key": "AIzaSyD9SE9zkuvrJ3t-xEKy78DhL7AoefiyjLg"
        }
      ],
      "services": {
        "appinvite_service": {
          "other_platform_oauth_client": []
        }
      }
    }
  ],
  "configuration_version": "1"
}